tinygrad/__init__.py
tinygrad/graph.py
tinygrad/helpers.py
tinygrad/lazy.py
tinygrad/mlops.py
tinygrad/ops.py
tinygrad/shapetracker.py
tinygrad/tensor.py
tinygrad/llops/ops_cpu.py
tinygrad/llops/ops_gpu.py
tinygrad/llops/ops_llvm.py
tinygrad/llops/ops_opencl.py
tinygrad/llops/ops_torch.py
tinygrad/nn/__init__.py
tinygrad/nn/optim.py
tinygrad_experiments-0.4.0.dist-info/LICENSE
tinygrad_experiments-0.4.0.dist-info/METADATA
tinygrad_experiments-0.4.0.dist-info/WHEEL
tinygrad_experiments-0.4.0.dist-info/top_level.txt
tinygrad_experiments-0.4.0.dist-info/RECORD
