Metadata-Version: 2.1
Name: tinygrad-experiments
Version: 0.4.0
Summary: You like pytorch? You like micrograd? You love tinygrad! heart
Author: George Hotz
License: MIT
Classifier: Programming Language :: Python :: 3
Classifier: License :: OSI Approved :: MIT License
Requires-Python: >=3.8
License-File: LICENSE
Requires-Dist: numpy
Requires-Dist: requests
Requires-Dist: pillow
Requires-Dist: networkx
Provides-Extra: gpu
Requires-Dist: pyopencl ; extra == 'gpu'
Requires-Dist: six ; extra == 'gpu'
Provides-Extra: llvm
Requires-Dist: llvmlite ; extra == 'llvm'
Provides-Extra: testing
Requires-Dist: pytest ; extra == 'testing'
Requires-Dist: torch (~=1.11.0) ; extra == 'testing'
Requires-Dist: tqdm ; extra == 'testing'
Requires-Dist: protobuf (~=3.19.0) ; extra == 'testing'
Requires-Dist: onnx ; extra == 'testing'
Requires-Dist: onnx2torch ; extra == 'testing'
Requires-Dist: mypy ; extra == 'testing'
